ptwordlists/__init__.py
ptwordlists/_version.py
ptwordlists/ptwordlists.py
ptwordlists/utils/__init__.py
ptwordlists/utils/symlink.py
ptwordlists/wordlists/__init__.py
ptwordlists/wordlists/admin.txt
ptwordlists/wordlists/config.txt
ptwordlists/wordlists/directories.txt
ptwordlists/wordlists/examples.txt
ptwordlists/wordlists/index.txt
ptwordlists/wordlists/info.txt
ptwordlists/wordlists/ip_192.168.0.0.txt
ptwordlists/wordlists/ip_router.txt
ptwordlists/wordlists/linux_files.txt
ptwordlists/wordlists/meta.txt
ptwordlists/wordlists/plugins.txt
ptwordlists/wordlists/readme.txt
ptwordlists/wordlists/repositories.txt
ptwordlists/wordlists/statistics.txt
ptwordlists/wordlists/technologies.txt
ptwordlists/wordlists/wp-plugins.txt
ptwordlists-0.0.1.dist-info/licenses/LICENSE
ptwordlists-0.0.1.dist-info/METADATA
ptwordlists-0.0.1.dist-info/WHEEL
ptwordlists-0.0.1.dist-info/entry_points.txt
ptwordlists-0.0.1.dist-info/top_level.txt
ptwordlists-0.0.1.dist-info/RECORD
